tf2onnx/__init__.py
tf2onnx/constants.py
tf2onnx/convert.py
tf2onnx/graph.py
tf2onnx/graph_builder.py
tf2onnx/graph_matcher.py
tf2onnx/handler.py
tf2onnx/loader.py
tf2onnx/schemas.py
tf2onnx/shape_inference.py
tf2onnx/tfonnx.py
tf2onnx/utils.py
tf2onnx/verbose_logging.py
tf2onnx/version.py
tf2onnx/custom_opsets/__init__.py
tf2onnx/custom_opsets/ms.py
tf2onnx/onnx_opset/__init__.py
tf2onnx/onnx_opset/common.py
tf2onnx/onnx_opset/controlflow.py
tf2onnx/onnx_opset/generator.py
tf2onnx/onnx_opset/logical.py
tf2onnx/onnx_opset/math.py
tf2onnx/onnx_opset/misc.py
tf2onnx/onnx_opset/nn.py
tf2onnx/onnx_opset/reduction.py
tf2onnx/onnx_opset/rnn.py
tf2onnx/onnx_opset/tensor.py
tf2onnx/onnx_opset/traditionalml.py
tf2onnx/optimizer/__init__.py
tf2onnx/optimizer/const_fold_optimizer.py
tf2onnx/optimizer/identity_optimizer.py
tf2onnx/optimizer/loop_optimizer.py
tf2onnx/optimizer/merge_duplicated_nodes_optimizer.py
tf2onnx/optimizer/optimizer_base.py
tf2onnx/optimizer/transpose_optimizer.py
tf2onnx/rewriter/__init__.py
tf2onnx/rewriter/bigru_rewriter.py
tf2onnx/rewriter/bilstm_rewriter.py
tf2onnx/rewriter/cond_rewriter.py
tf2onnx/rewriter/conv2d_with_pad_rewriter.py
tf2onnx/rewriter/custom_rnn_rewriter.py
tf2onnx/rewriter/dropout_rewriter.py
tf2onnx/rewriter/eye_rewriter.py
tf2onnx/rewriter/flatten_rewriter.py
tf2onnx/rewriter/gemm_rewriter.py
tf2onnx/rewriter/gru_rewriter.py
tf2onnx/rewriter/leakyrelu_rewriter.py
tf2onnx/rewriter/loop_rewriter.py
tf2onnx/rewriter/loop_rewriter_base.py
tf2onnx/rewriter/lstm_rewriter.py
tf2onnx/rewriter/random_normal_rewriter.py
tf2onnx/rewriter/random_uniform.py
tf2onnx/rewriter/rnn.py
tf2onnx/rewriter/rnn_utils.py
tf2onnx/rewriter/thresholded_relu_rewriter.py
tf2onnx/rewriter/transpose_rewriter.py
tf2onnx/rewriter/unit_rnn_rewriter_base.py
tf2onnx_xzj-1.6.0.dist-info/DESCRIPTION.rst
tf2onnx_xzj-1.6.0.dist-info/METADATA
tf2onnx_xzj-1.6.0.dist-info/RECORD
tf2onnx_xzj-1.6.0.dist-info/WHEEL
tf2onnx_xzj-1.6.0.dist-info/metadata.json
tf2onnx_xzj-1.6.0.dist-info/top_level.txt
