Metadata-Version: 2.0
Name: tf2onnx-xzj
Version: 1.6.0
Summary: Tensorflow to ONNX converter
Home-page: https://github.com/onnx/tensorflow-onnx
Author: onnx@microsoft.com
Author-email: onnx@microsoft.com
License: UNKNOWN
Platform: UNKNOWN
Requires-Dist: numpy (>=1.14.1)
Requires-Dist: onnx (>=1.4.1)
Requires-Dist: requests
Requires-Dist: six
